srdetector/__init__.py
srdetector/main.py
srdetector-0.3.dist-info/METADATA
srdetector-0.3.dist-info/WHEEL
srdetector-0.3.dist-info/top_level.txt
srdetector-0.3.dist-info/RECORD
